gias3.mapclientpluginutilities-3.0.0-py3.9-nspkg.pth
gias3/mapclientpluginutilities/__init__.py
gias3/mapclientpluginutilities/configtools/__init__.py
gias3/mapclientpluginutilities/configtools/validators.py
gias3/mapclientpluginutilities/datatypes/__init__.py
gias3/mapclientpluginutilities/datatypes/transformations.py
gias3/mapclientpluginutilities/viewers/__init__.py
gias3/mapclientpluginutilities/viewers/mayaviscenewidget.py
gias3/mapclientpluginutilities/viewers/mayaviviewerdatapoints.py
gias3/mapclientpluginutilities/viewers/mayaviviewerfieldworkmeasurements.py
gias3/mapclientpluginutilities/viewers/mayaviviewerfieldworkmodel.py
gias3/mapclientpluginutilities/viewers/mayaviviewergiasscan.py
gias3/mapclientpluginutilities/viewers/mayaviviewerimageplane.py
gias3/mapclientpluginutilities/viewers/mayaviviewerlandmark.py
gias3/mapclientpluginutilities/viewers/mayaviviewerobjects.py
gias3.mapclientpluginutilities-3.0.0.dist-info/LICENSE
gias3.mapclientpluginutilities-3.0.0.dist-info/METADATA
gias3.mapclientpluginutilities-3.0.0.dist-info/WHEEL
gias3.mapclientpluginutilities-3.0.0.dist-info/namespace_packages.txt
gias3.mapclientpluginutilities-3.0.0.dist-info/top_level.txt
gias3.mapclientpluginutilities-3.0.0.dist-info/RECORD
